graphql_env/__init__.py
graphql_env/_compat.py
graphql_env/environment.py
graphql_env/utils.py
graphql_env-0.1.0.dist-info/DESCRIPTION.rst
graphql_env-0.1.0.dist-info/METADATA
graphql_env-0.1.0.dist-info/RECORD
graphql_env-0.1.0.dist-info/WHEEL
graphql_env-0.1.0.dist-info/metadata.json
graphql_env-0.1.0.dist-info/top_level.txt
